infrastructure/__init__.py
infrastructure/_version.py
infrastructure/decorators.py
infrastructure/exceptions.py
infrastructure/function_finder.py
infrastructure/function_manager.py
infrastructure/function_scheduler.py
infrastructure/plugin.py
infrastructure/strings.py
pytest_infrastructure-0.0.2.dist-info/LICENSE
pytest_infrastructure-0.0.2.dist-info/METADATA
pytest_infrastructure-0.0.2.dist-info/WHEEL
pytest_infrastructure-0.0.2.dist-info/entry_points.txt
pytest_infrastructure-0.0.2.dist-info/top_level.txt
pytest_infrastructure-0.0.2.dist-info/RECORD
