Metadata-Version: 2.1
Name: pytest-infrastructure
Version: 0.0.2
Summary: pytest stack validation prior to testing executing
Home-page: https://github.com/symonk/pytest-infrastructure
Author: Simon Kerr
Author-email: jackofspaces@gmail.com
Maintainer: Simon Kerr
Maintainer-email: jackofspaces@gmail.com
License: Apache Software License 2.0
Platform: UNKNOWN
Classifier: Development Status :: 4 - Beta
Classifier: Framework :: Pytest
Classifier: Topic :: Software Development :: Testing
Classifier: Topic :: Software Development :: Quality Assurance
Classifier: Programming Language :: Python :: 3.7
Classifier: Operating System :: OS Independent
Classifier: License :: OSI Approved :: Apache Software License
